conda_package_handling/__init__.py
conda_package_handling/__main__.py
conda_package_handling/api.py
conda_package_handling/cli.py
conda_package_handling/conda_fmt.py
conda_package_handling/exceptions.py
conda_package_handling/interface.py
conda_package_handling/streaming.py
conda_package_handling/tarball.py
conda_package_handling/utils.py
conda_package_handling/validate.py
conda_package_handling-2.3.0.dist-info/AUTHORS.md
conda_package_handling-2.3.0.dist-info/LICENSE
conda_package_handling-2.3.0.dist-info/METADATA
conda_package_handling-2.3.0.dist-info/WHEEL
conda_package_handling-2.3.0.dist-info/entry_points.txt
conda_package_handling-2.3.0.dist-info/top_level.txt
conda_package_handling-2.3.0.dist-info/RECORD
